gtki_module_exex/__init__.py
gtki_module_exex/main.py
gtki_module_exex/mixins.py
gtki_module_exex/tests/__init__.py
gtki_module_exex/tests/main_tests.py
gtki_module_exex/tests/mixins_tests.py
gtki_module_exex-0.0.69.dist-info/LICENSE
gtki_module_exex-0.0.69.dist-info/METADATA
gtki_module_exex-0.0.69.dist-info/WHEEL
gtki_module_exex-0.0.69.dist-info/top_level.txt
gtki_module_exex-0.0.69.dist-info/RECORD
